{
"meta":{"test_sets":[],"test_metrics":[],"learn_metrics":[{"best_value":"Min","name":"RMSE"}],"launch_mode":"Train","parameters":"","iteration_count":100,"learn_sets":["learn"],"name":"experiment"},
"iterations":[
{"learn":[14.005006],"iteration":0,"passed_time":0.001436675488,"remaining_time":0.1422308733},
{"learn":[13.14441192],"iteration":1,"passed_time":0.003110313022,"remaining_time":0.1524053381},
{"learn":[12.34258257],"iteration":2,"passed_time":0.005065694156,"remaining_time":0.1637907777},
{"learn":[11.64527793],"iteration":3,"passed_time":0.006528651919,"remaining_time":0.1566876461},
{"learn":[11.02766183],"iteration":4,"passed_time":0.008645714467,"remaining_time":0.1642685749},
{"learn":[10.43485794],"iteration":5,"passed_time":0.01023057966,"remaining_time":0.1602790813},
{"learn":[9.890641275],"iteration":6,"passed_time":0.01178331076,"remaining_time":0.1565497001},
{"learn":[9.492161212],"iteration":7,"passed_time":0.01333285446,"remaining_time":0.1533278263},
{"learn":[9.105082953],"iteration":8,"passed_time":0.01457853745,"remaining_time":0.1474052119},
{"learn":[8.674157135],"iteration":9,"passed_time":0.01616987224,"remaining_time":0.1455288502},
{"learn":[8.341743544],"iteration":10,"passed_time":0.01777632306,"remaining_time":0.1438266139},
{"learn":[8.049372916],"iteration":11,"passed_time":0.01965167823,"remaining_time":0.144112307},
{"learn":[7.757318612],"iteration":12,"passed_time":0.0219837078,"remaining_time":0.1471217368},
{"learn":[7.522206899],"iteration":13,"passed_time":0.02408109008,"remaining_time":0.1479266962},
{"learn":[7.297756655],"iteration":14,"passed_time":0.02563419259,"remaining_time":0.1452604247},
{"learn":[7.088359431],"iteration":15,"passed_time":0.0284143796,"remaining_time":0.1491754929},
{"learn":[6.882113791],"iteration":16,"passed_time":0.02984128706,"remaining_time":0.1456956956},
{"learn":[6.704728832],"iteration":17,"passed_time":0.03146898566,"remaining_time":0.1433587124},
{"learn":[6.563881962],"iteration":18,"passed_time":0.03284841802,"remaining_time":0.1400379926},
{"learn":[6.418790279],"iteration":19,"passed_time":0.03425924313,"remaining_time":0.1370369725},
{"learn":[6.315756953],"iteration":20,"passed_time":0.03629669759,"remaining_time":0.1365447195},
{"learn":[6.210157751],"iteration":21,"passed_time":0.039102465,"remaining_time":0.1386360123},
{"learn":[6.115058449],"iteration":22,"passed_time":0.0408301446,"remaining_time":0.1366922232},
{"learn":[6.014819884],"iteration":23,"passed_time":0.04303347626,"remaining_time":0.1362726748},
{"learn":[5.93117229],"iteration":24,"passed_time":0.04459784829,"remaining_time":0.1337935449},
{"learn":[5.844857622],"iteration":25,"passed_time":0.04644441353,"remaining_time":0.1321879462},
{"learn":[5.771145213],"iteration":26,"passed_time":0.04814130895,"remaining_time":0.1301598353},
{"learn":[5.704018229],"iteration":27,"passed_time":0.04952735218,"remaining_time":0.1273560485},
{"learn":[5.665806474],"iteration":28,"passed_time":0.05194146097,"remaining_time":0.1271670251},
{"learn":[5.616500369],"iteration":29,"passed_time":0.05320237359,"remaining_time":0.1241388717},
{"learn":[5.558023666],"iteration":30,"passed_time":0.05469010918,"remaining_time":0.1217295978},
{"learn":[5.510080976],"iteration":31,"passed_time":0.05621145823,"remaining_time":0.1194493487},
{"learn":[5.468747792],"iteration":32,"passed_time":0.05779578087,"remaining_time":0.117342949},
{"learn":[5.429275534],"iteration":33,"passed_time":0.05988433933,"remaining_time":0.1162460705},
{"learn":[5.402117324],"iteration":34,"passed_time":0.06120175114,"remaining_time":0.113660395},
{"learn":[5.367635151],"iteration":35,"passed_time":0.06271371058,"remaining_time":0.111491041},
{"learn":[5.345181232],"iteration":36,"passed_time":0.06457187212,"remaining_time":0.1099467012},
{"learn":[5.319151269],"iteration":37,"passed_time":0.0659422671,"remaining_time":0.1075900147},
{"learn":[5.296134146],"iteration":38,"passed_time":0.06782139869,"remaining_time":0.1060796236},
{"learn":[5.269629003],"iteration":39,"passed_time":0.06925917698,"remaining_time":0.1038887655},
{"learn":[5.251147059],"iteration":40,"passed_time":0.07119642213,"remaining_time":0.1024533879},
{"learn":[5.248003302],"iteration":41,"passed_time":0.07169900116,"remaining_time":0.09901290637},
{"learn":[5.232376509],"iteration":42,"passed_time":0.07337825963,"remaining_time":0.09726885578},
{"learn":[5.213524255],"iteration":43,"passed_time":0.07513323578,"remaining_time":0.09562411827},
{"learn":[5.189691584],"iteration":44,"passed_time":0.07703994313,"remaining_time":0.09415993049},
{"learn":[5.166052198],"iteration":45,"passed_time":0.07862441405,"remaining_time":0.09229822518},
{"learn":[5.140406659],"iteration":46,"passed_time":0.08183211264,"remaining_time":0.09227876531},
{"learn":[5.118929684],"iteration":47,"passed_time":0.08480873308,"remaining_time":0.09187612751},
{"learn":[5.108792602],"iteration":48,"passed_time":0.08634831032,"remaining_time":0.08987273115},
{"learn":[5.098141225],"iteration":49,"passed_time":0.08762945939,"remaining_time":0.08762945939},
{"learn":[5.085926393],"iteration":50,"passed_time":0.0890701042,"remaining_time":0.08557715894},
{"learn":[5.067816804],"iteration":51,"passed_time":0.09103432207,"remaining_time":0.08403168191},
{"learn":[5.049834901],"iteration":52,"passed_time":0.09258846394,"remaining_time":0.08210675104},
{"learn":[5.03838627],"iteration":53,"passed_time":0.09407866182,"remaining_time":0.08014108229},
{"learn":[5.033534248],"iteration":54,"passed_time":0.09553820461,"remaining_time":0.07816762195},
{"learn":[5.023726885],"iteration":55,"passed_time":0.1103567871,"remaining_time":0.08670890417},
{"learn":[5.01290392],"iteration":56,"passed_time":0.1131402397,"remaining_time":0.08535140892},
{"learn":[5.005569127],"iteration":57,"passed_time":0.1150021888,"remaining_time":0.08327744703},
{"learn":[4.989969032],"iteration":58,"passed_time":0.1170931147,"remaining_time":0.08136979159},
{"learn":[4.976762446],"iteration":59,"passed_time":0.1189938452,"remaining_time":0.07932923014},
{"learn":[4.967222715],"iteration":60,"passed_time":0.1223412136,"remaining_time":0.07821815296},
{"learn":[4.954407599],"iteration":61,"passed_time":0.1269664223,"remaining_time":0.07781812979},
{"learn":[4.942125056],"iteration":62,"passed_time":0.1290967291,"remaining_time":0.0758187139},
{"learn":[4.930230716],"iteration":63,"passed_time":0.130260882,"remaining_time":0.07327174613},
{"learn":[4.921695642],"iteration":64,"passed_time":0.1312771776,"remaining_time":0.070687711},
{"learn":[4.906405625],"iteration":65,"passed_time":0.1322460556,"remaining_time":0.06812675589},
{"learn":[4.894330248],"iteration":66,"passed_time":0.1331991975,"remaining_time":0.0656055749},
{"learn":[4.88211557],"iteration":67,"passed_time":0.1342198611,"remaining_time":0.06316228757},
{"learn":[4.877946398],"iteration":68,"passed_time":0.1351204149,"remaining_time":0.06070627336},
{"learn":[4.863182126],"iteration":69,"passed_time":0.1360786032,"remaining_time":0.05831940136},
{"learn":[4.84646533],"iteration":70,"passed_time":0.1374006032,"remaining_time":0.05612137313},
{"learn":[4.838014752],"iteration":71,"passed_time":0.1387551615,"remaining_time":0.05396034057},
{"learn":[4.82981137],"iteration":72,"passed_time":0.1397917964,"remaining_time":0.0517038151},
{"learn":[4.817094767],"iteration":73,"passed_time":0.1407892928,"remaining_time":0.04946650828},
{"learn":[4.808314151],"iteration":74,"passed_time":0.1418614609,"remaining_time":0.04728715363},
{"learn":[4.796235023],"iteration":75,"passed_time":0.1429270934,"remaining_time":0.0451348716},
{"learn":[4.784434534],"iteration":76,"passed_time":0.1469017923,"remaining_time":0.04387975613},
{"learn":[4.774402487],"iteration":77,"passed_time":0.1482994661,"remaining_time":0.04182805454},
{"learn":[4.76731896],"iteration":78,"passed_time":0.1493483498,"remaining_time":0.03970019424},
{"learn":[4.75934113],"iteration":79,"passed_time":0.1503960993,"remaining_time":0.03759902482},
{"learn":[4.754106378],"iteration":80,"passed_time":0.151478495,"remaining_time":0.03553199265},
{"learn":[4.744002932],"iteration":81,"passed_time":0.1525002835,"remaining_time":0.03347567199},
{"learn":[4.731700554],"iteration":82,"passed_time":0.1546845977,"remaining_time":0.03168238747},
{"learn":[4.723284153],"iteration":83,"passed_time":0.1559019211,"remaining_time":0.02969560403},
{"learn":[4.712232782],"iteration":84,"passed_time":0.1569616329,"remaining_time":0.02769911168},
{"learn":[4.703046867],"iteration":85,"passed_time":0.1580080963,"remaining_time":0.02572224823},
{"learn":[4.698601855],"iteration":86,"passed_time":0.1589882087,"remaining_time":0.02375685878},
{"learn":[4.692429407],"iteration":87,"passed_time":0.1600774473,"remaining_time":0.02182874281},
{"learn":[4.675027364],"iteration":88,"passed_time":0.1613204154,"remaining_time":0.0199384783},
{"learn":[4.662368584],"iteration":89,"passed_time":0.1622999259,"remaining_time":0.0180333251},
{"learn":[4.646206172],"iteration":90,"passed_time":0.1635876781,"remaining_time":0.01617900113},
{"learn":[4.641245848],"iteration":91,"passed_time":0.1645287398,"remaining_time":0.01430684694},
{"learn":[4.633900435],"iteration":92,"passed_time":0.1655385492,"remaining_time":0.0124598908},
{"learn":[4.624738236],"iteration":93,"passed_time":0.1665655898,"remaining_time":0.01063184616},
{"learn":[4.612798287],"iteration":94,"passed_time":0.1674753009,"remaining_time":0.008814489519},
{"learn":[4.605222001],"iteration":95,"passed_time":0.1689384689,"remaining_time":0.007039102869},
{"learn":[4.601725912],"iteration":96,"passed_time":0.1700330683,"remaining_time":0.00525875469},
{"learn":[4.59722371],"iteration":97,"passed_time":0.1709253279,"remaining_time":0.003488271999},
{"learn":[4.580235665],"iteration":98,"passed_time":0.1720194247,"remaining_time":0.001737569946},
{"learn":[4.57591791],"iteration":99,"passed_time":0.1730908201,"remaining_time":0}
]}